greedypacker/__init__.py
greedypacker/binmanager.py
greedypacker/guillotine.py
greedypacker/item.py
greedypacker/shelf.py
greedypacker-0.1.dist-info/DESCRIPTION.rst
greedypacker-0.1.dist-info/METADATA
greedypacker-0.1.dist-info/RECORD
greedypacker-0.1.dist-info/WHEEL
greedypacker-0.1.dist-info/metadata.json
greedypacker-0.1.dist-info/top_level.txt
