Metadata-Version: 2.0
Name: greedypacker
Version: 0.1
Summary: A two dimensional binpacking library
Home-page: https://github.com/ssbothwell/BinPack
Author: Solomon Bothwell
Author-email: ssbothwell@gmail.com
License: Apache2
Download-URL: https://github.com/ssbothwell/BinPack/archive/0.1.tar.gz
Keywords: binpacking,algorithm,greedy,library
Platform: UNKNOWN
Requires-Python: >=3
